[
    {
        "imagePath": "/iimteresante/assets/images/Blog-banner.png",
        "url": "/iimteresante/pages/blog.html",
        "text": "Blog",
        "textPosition": "top-right"

    },
    {
        "imagePath": "/iimteresante/assets/images/galeria.png",
        "url": "/iimteresante/pages/galeria.html",
        "text": "Galeria",
        "textPosition": "top-right"
    },
    {
        "imagePath": "/iimteresante/assets/images/Podcast.png",
        "url": "/iimteresante/pages/Podcasts.html",
        "text": "Podcasts",
        "textPosition": "top-right"
    }
    ,
    {
        "imagePath": "/iimteresante/assets/images/Infografías.png",
        "url": "/iimteresante/pages/infografias.html",
        "text": "Infografias",
        "textPosition": "top-right"

    },
    {
        "imagePath": "/iimteresante/assets/images/Ciencia en corto.png",
        "url": "/iimteresante/pages/pitch-cientifico.html",
        "text": "Ciencia en corto",
        "textPosition": "top-right"
    },
    {
        "imagePath": "/iimteresante/assets/images/contacto.png",
        "url": "/iimteresante/pages/contacto.html",
        "text": "Contacto",
        "textPosition": "top-right"

    }
]